dspy_react_machina/__init__.py
dspy_react_machina/_debug_utils.py
dspy_react_machina/adapter.py
dspy_react_machina/conversation.py
dspy_react_machina/exceptions.py
dspy_react_machina/py.typed
dspy_react_machina/react_machina.py
dspy_react_machina/signatures.py
dspy_react_machina/state_machine.py
dspy_react_machina/tools.py
dspy_react_machina-0.1.2.dist-info/WHEEL
dspy_react_machina-0.1.2.dist-info/entry_points.txt
dspy_react_machina-0.1.2.dist-info/METADATA
dspy_react_machina-0.1.2.dist-info/RECORD
