Metadata-Version: 2.3
Name: dspy-react-machina
Version: 0.1.2
Summary: Alternative ReAct implementation for DSPy with full conversation history
Keywords: dspy,react,llm,agent,state-machine,conversation
Author: Arthur Moura Carvalho
Author-email: Arthur Moura Carvalho <armoucar@gmail.com>
License: MIT
Classifier: Development Status :: 3 - Alpha
Classifier: Intended Audience :: Developers
Classifier: License :: OSI Approved :: MIT License
Classifier: Programming Language :: Python :: 3
Classifier: Programming Language :: Python :: 3.12
Classifier: Topic :: Scientific/Engineering :: Artificial Intelligence
Requires-Dist: dspy>=3.0.0
Requires-Python: >=3.12
Project-URL: Homepage, https://github.com/armoucar/dspy-react-machina
Project-URL: Issues, https://github.com/armoucar/dspy-react-machina/issues
Project-URL: Repository, https://github.com/armoucar/dspy-react-machina
